myback/__init__.py
myback/dialog.py
myback/main.py
myback/tools.py
myback-1.0.0.dist-info/licenses/LICENSE
myback-1.0.0.dist-info/METADATA
myback-1.0.0.dist-info/WHEEL
myback-1.0.0.dist-info/entry_points.txt
myback-1.0.0.dist-info/top_level.txt
myback-1.0.0.dist-info/RECORD
